<?xml version="1.0" encoding="UTF-8"?><Root>
      		<SubSystem>
		<Name>Scope </Name>
		<xPCName>E_stopnew/Scope </xPCName>
		
		

		</SubSystem>

      
            <block>
            <blkName>Constant</blkName>
            <xpcblkName>Constant</xpcblkName>
            <SLblockPath>E_stopnew/Constant</SLblockPath>
            <isSrc>[1 0 1]</isSrc>
          <parameter>
          <paramName>Value</paramName>
          <dim>[1, 1]</dim>  
		  <SubSystemName>E_stopnew</SubSystemName>
          </parameter>
          </block>
            <block>
            <blkName>Constant1</blkName>
            <xpcblkName>Constant1</xpcblkName>
            <SLblockPath>E_stopnew/Constant1</SLblockPath>
            <isSrc>[1 0 1]</isSrc>
          <parameter>
          <paramName>Value</paramName>
          <dim>[1, 1]</dim>  
		  <SubSystemName>E_stopnew</SubSystemName>
          </parameter>
          </block>
            <block>
            <blkName>Q4 AD</blkName>
            <xpcblkName>Q4 AD</xpcblkName>
            <SLblockPath>E_stopnew/Q4 AD</SLblockPath>
            <isSrc>[1 0 1]</isSrc>
          <parameter>
          <paramName>P1</paramName>
          <dim>[1, 1]</dim>  
		  <SubSystemName>E_stopnew</SubSystemName>
          </parameter>
          <parameter>
          <paramName>P2</paramName>
          <dim>[1, 1]</dim>  
		  <SubSystemName>E_stopnew</SubSystemName>
          </parameter>
          <parameter>
          <paramName>P3</paramName>
          <dim>[1, 1]</dim>  
		  <SubSystemName>E_stopnew</SubSystemName>
          </parameter>
          <parameter>
          <paramName>P5</paramName>
          <dim>[1, 1]</dim>  
		  <SubSystemName>E_stopnew</SubSystemName>
          </parameter>
          <parameter>
          <paramName>P6</paramName>
          <dim>[1, 1]</dim>  
		  <SubSystemName>E_stopnew</SubSystemName>
          </parameter>
          <parameter>
          <paramName>P7</paramName>
          <dim>[1, 1]</dim>  
		  <SubSystemName>E_stopnew</SubSystemName>
          </parameter>
          </block>
            <block>
            <blkName>Q4 DA </blkName>
            <xpcblkName>Q4 DA </xpcblkName>
            <SLblockPath>E_stopnew/Q4 DA </SLblockPath>
            <isSrc>[0 1 0]</isSrc>
          <parameter>
          <paramName>P1</paramName>
          <dim>[1, 1]</dim>  
		  <SubSystemName>E_stopnew</SubSystemName>
          </parameter>
          <parameter>
          <paramName>P2</paramName>
          <dim>[1, 1]</dim>  
		  <SubSystemName>E_stopnew</SubSystemName>
          </parameter>
          <parameter>
          <paramName>P3</paramName>
          <dim>[1, 1]</dim>  
		  <SubSystemName>E_stopnew</SubSystemName>
          </parameter>
          <parameter>
          <paramName>P4</paramName>
          <dim>[1, 1]</dim>  
		  <SubSystemName>E_stopnew</SubSystemName>
          </parameter>
          <parameter>
          <paramName>P5</paramName>
          <dim>[1, 1]</dim>  
		  <SubSystemName>E_stopnew</SubSystemName>
          </parameter>
          <parameter>
          <paramName>P6</paramName>
          <dim>[1, 1]</dim>  
		  <SubSystemName>E_stopnew</SubSystemName>
          </parameter>
          <parameter>
          <paramName>P7</paramName>
          <dim>[1, 1]</dim>  
		  <SubSystemName>E_stopnew</SubSystemName>
          </parameter>
          <parameter>
          <paramName>P8</paramName>
          <dim>[1, 1]</dim>  
		  <SubSystemName>E_stopnew</SubSystemName>
          </parameter>
          <parameter>
          <paramName>P9</paramName>
          <dim>[1, 1]</dim>  
		  <SubSystemName>E_stopnew</SubSystemName>
          </parameter>
          </block>
			  
			  
              <signal>
              <sigName>Constant1</sigName>
              <xpcsigName>Constant1</xpcsigName>
              <sigWidth>1</sigWidth>
              <sigDim>[1, 1]</sigDim>
			  <SubSystemName>E_stopnew</SubSystemName>
			  <sigTestPoint>false</sigTestPoint>
            </signal>
			  
			  
              <signal>
              <sigName>Relational
Operator</sigName>
              <xpcsigName>Relational Operator</xpcsigName>
              <sigWidth>1</sigWidth>
              <sigDim>[1, 1]</sigDim>
			  <SubSystemName>E_stopnew</SubSystemName>
			  <sigTestPoint>false</sigTestPoint>
            </signal>
			  
			  
              <signal>
              <sigName>Q4 AD</sigName>
              <xpcsigName>Q4 AD</xpcsigName>
              <sigWidth>1</sigWidth>
              <sigDim>[1, 1]</sigDim>
			  <SubSystemName>E_stopnew</SubSystemName>
			  <sigTestPoint>false</sigTestPoint>
            </signal>

</Root>